cli/__init__.py
cli/__main__.py
cli/knu.py
cli/lib/__init__.py
cli/lib/account.py
cli/lib/recorder.py
knuverse_cli-1.0.8.dist-info/DESCRIPTION.rst
knuverse_cli-1.0.8.dist-info/METADATA
knuverse_cli-1.0.8.dist-info/RECORD
knuverse_cli-1.0.8.dist-info/WHEEL
knuverse_cli-1.0.8.dist-info/entry_points.txt
knuverse_cli-1.0.8.dist-info/metadata.json
knuverse_cli-1.0.8.dist-info/top_level.txt
