Metadata-Version: 2.0
Name: knuverse-cli
Version: 1.0.8
Summary: Demo of the Knuverse SDK that lets you verify with AudioPIN and AudioPass
Home-page: https://github.com/KnuVerse/knuverse-cli
Author: KnuVerse
Author-email: support@knuverse.com
License: MIT
Keywords: api sdk knuverse cloud voice authentication audiopin audiopass demo
Platform: UNKNOWN
Classifier: Development Status :: 3 - Alpha
Classifier: Intended Audience :: Developers
Classifier: Topic :: Software Development :: Build Tools
Classifier: License :: OSI Approved :: MIT License
Classifier: Programming Language :: Python :: 2.7
Classifier: Programming Language :: Python :: 3
Classifier: Programming Language :: Python :: 3.3
Classifier: Programming Language :: Python :: 3.4
Classifier: Programming Language :: Python :: 3.5
Requires-Dist: colorama
Requires-Dist: knuverse (==1.0.7)
Requires-Dist: pyaudio
